LICENSE
MANIFEST.in
README.rst
setup.cfg
setup.py
chat_api/__init__.py
chat_api/admin.py
chat_api/api_urls.py
chat_api/common.py
chat_api/models.py
chat_api/permissions.py
chat_api/search.py
chat_api/settings.py
chat_api.egg-info/PKG-INFO
chat_api.egg-info/SOURCES.txt
chat_api.egg-info/dependency_links.txt
chat_api.egg-info/not-zip-safe
chat_api.egg-info/requires.txt
chat_api.egg-info/top_level.txt
chat_api/chat/__init__.py
chat_api/chat/api.py
chat_api/chat/api_urls.py
chat_api/chat/models.py
chat_api/chat/notifications.py
chat_api/chat/optimizations.py
chat_api/chat/serializers.py
chat_api/chat/signals.py
chat_api/chat/tasks.py
chat_api/management/__init__.py
chat_api/management/commands/__init__.py
chat_api/management/commands/dump_schema.py
chat_api/management/commands/load_schema.py
chat_api/migrations/0001_initial.py
chat_api/migrations/0002_auto_20170206_0538.py
chat_api/migrations/0003_auto_20170227_1037.py
chat_api/migrations/0004_message_predecessor.py
chat_api/migrations/0005_auto_20170301_0705.py
chat_api/migrations/0006_auto_20170302_0919.py
chat_api/migrations/0007_auto_20170303_1657.py
chat_api/migrations/0008_auto_20170309_0622.py
chat_api/migrations/0009_survey_fields_visibility.py
chat_api/migrations/0010_auto_20170313_0919.py
chat_api/migrations/0011_userthread_last_message.py
chat_api/migrations/0012_auto_20170331_0436.py
chat_api/migrations/0013_auto_20170509_1125.py
chat_api/migrations/0014_auto_20170523_0812.py
chat_api/migrations/0015_forking.py
chat_api/migrations/0016_forking_fix.py
chat_api/migrations/0017_survey_unique_together.py
chat_api/migrations/__init__.py
chat_api/schemas/__init__.py
chat_api/schemas/api.py
chat_api/schemas/api_urls.py
chat_api/schemas/models.py
chat_api/schemas/serializers.py
chat_api/schemas/signals.py
chat_api/schemas/utils.py
chat_api/surveys/__init__.py
chat_api/surveys/api.py
chat_api/surveys/api_urls.py
chat_api/surveys/models.py
chat_api/surveys/optimizations.py
chat_api/surveys/serializers.py
chat_api/utils/__init__.py
chat_api/utils/decorators.py
chat_api/utils/fields.py
chat_api/utils/middlewares.py
chat_api/utils/safe_delete_policy.py
chat_api/utils/serializer_fields.py
