Metadata-Version: 1.1
Name: chat-api
Version: 0.8.8
Summary: Automated Chat & Surveys API
Home-page: https://bitbucket.org/arabellatech/chat_api
Author: Pawel Krzyzaniak
Author-email: pawelk@arabel.la
License: Proprietary
Platform: UNKNOWN
Classifier: Development Status :: 3 - Alpha
Classifier: Environment :: Web Environment
Classifier: Framework :: Django
Classifier: Intended Audience :: Developers
Classifier: Operating System :: OS Independent
Classifier: Programming Language :: Python
Classifier: Programming Language :: Python :: 2.7
Classifier: Programming Language :: Python :: 3.5
Classifier: Programming Language :: Python :: 3.6
Classifier: Topic :: Internet :: WWW/HTTP
